fetch_sitemap/__init__.py
fetch_sitemap/datastructures.py
fetch_sitemap/fetch.py
fetch_sitemap-27.dist-info/LICENSE
fetch_sitemap-27.dist-info/METADATA
fetch_sitemap-27.dist-info/WHEEL
fetch_sitemap-27.dist-info/entry_points.txt
fetch_sitemap-27.dist-info/RECORD
