Metadata-Version: 2.1
Name: fetch-sitemap
Version: 27
Summary: Fetch a given sitemap and retrieve all URLs in it.
License: MIT
Author: Martin Mahner
Author-email: martin@mahner.org
Requires-Python: >=3.9,<4.0
Classifier: License :: OSI Approved :: MIT License
Classifier: Operating System :: OS Independent
Classifier: Programming Language :: Python :: 3
Classifier: Programming Language :: Python :: 3.9
Classifier: Programming Language :: Python :: 3.10
Classifier: Programming Language :: Python :: 3.11
Classifier: Programming Language :: Python :: 3.12
Classifier: Programming Language :: Python :: 3.13
Requires-Dist: aiofiles
Requires-Dist: aiohttp (>=3.9.0)
Requires-Dist: click
Requires-Dist: defusedxml
Requires-Dist: rich
Requires-Dist: rich-click
